chqtest/__init__.py
chqtest/chqtest.py
chqtest/cli.py
chqtest-0.1.0.dist-info/DESCRIPTION.rst
chqtest-0.1.0.dist-info/RECORD
chqtest-0.1.0.dist-info/WHEEL
chqtest-0.1.0.dist-info/METADATA
chqtest-0.1.0.dist-info/entry_points.txt
chqtest-0.1.0.dist-info/metadata.json
chqtest-0.1.0.dist-info/top_level.txt
